mycliapp/__init__.py
mycliapp/main.py
mycliapp-0.4.dist-info/METADATA
mycliapp-0.4.dist-info/WHEEL
mycliapp-0.4.dist-info/entry_points.txt
mycliapp-0.4.dist-info/top_level.txt
mycliapp-0.4.dist-info/RECORD
