Metadata-Version: 2.1
Name: mycliapp
Version: 0.4
Summary: UNKNOWN
Home-page: UNKNOWN
License: UNKNOWN
Platform: UNKNOWN
Requires-Dist: click
Requires-Dist: databricks-sql-connector
